synfo
