Metadata-Version: 1.0
Name: synfo
Version: 2.0.1
Summary: A lightweight utility for retrieving system information and specifications.
Home-page: https://github.com/mrstephenneal/synfo
Author: Stephen Neal
Author-email: stephen@stephenneal.net
License: GPL-3.0
Platform: UNKNOWN
